pandaSuit/__init__.py
pandaSuit/df.py
pandaSuit/common/__init__.py
pandaSuit/common/decorators.py
pandaSuit/common/unwind.py
pandaSuit/common/constant/__init__.py
pandaSuit/common/constant/date_constants.py
pandaSuit/common/constant/decorators.py
pandaSuit/common/constant/df.py
pandaSuit/common/constant/plot.py
pandaSuit/common/mappings/__init__.py
pandaSuit/common/mappings/reversible.py
pandaSuit/common/util/__init__.py
pandaSuit/common/util/list_operations.py
pandaSuit/plot/__init__.py
pandaSuit/plot/bar.py
pandaSuit/plot/histogram.py
pandaSuit/plot/line.py
pandaSuit/plot/pie.py
pandaSuit/plot/plot.py
pandaSuit/plot/scatter.py
pandaSuit/plot/dashboard/__init__.py
pandaSuit/plot/dashboard/dashboard.py
pandaSuit/plot/dashboard/tile.py
pandaSuit/stats/__init__.py
pandaSuit/stats/classification.py
pandaSuit/stats/linear.py
pandaSuit/stats/logistic.py
pandaSuit-1.2.15.dist-info/LICENSE
pandaSuit-1.2.15.dist-info/METADATA
pandaSuit-1.2.15.dist-info/WHEEL
pandaSuit-1.2.15.dist-info/top_level.txt
pandaSuit-1.2.15.dist-info/RECORD
