Metadata-Version: 2.1
Name: pandaSuit
Version: 1.2.15
Summary: pandas extension for DataFrame manipulation, statistics, and visualization
Home-page: https://github.com/AnthonyRaimondo/pandaSuit
Author: Anthony Raimondo
Author-email: anthonyraimondo7@gmail.com
License: MIT
Platform: UNKNOWN
License-File: LICENSE
Requires-Dist: pandas
Requires-Dist: scikit-learn
Requires-Dist: matplotlib
